stats5b5t/__init__.py
stats5b5t/__main__.py
stats5b5t/api.py
stats5b5t/tools.py
stats5b5t-0.1.0.dist-info/METADATA
stats5b5t-0.1.0.dist-info/WHEEL
stats5b5t-0.1.0.dist-info/top_level.txt
stats5b5t-0.1.0.dist-info/RECORD
